{"matchId":"018ce847-fe23-405e-a6c0-48ba53766681.nakama-0","mapId":"AmbroseValley","dates":["February_11"],"primaryDate":"February_11","durationMs":140,"startTimeMs":1770812681,"endTimeMs":1770812821,"humans":1,"bots":0,"participantCount":1,"rowCount":28,"eventCounts":{"BotKill":1,"BotKilled":1,"Loot":4,"Position":22},"participants":[{"userId":"86b019b9-dd32-4fe0-baf4-174a1f51fa68","isBot":false,"rowCount":28,"eventCounts":{"BotKill":1,"BotKilled":1,"Loot":4,"Position":22}}],"trackPoints":[{"userId":"86b019b9-dd32-4fe0-baf4-174a1f51fa68","isBot":false,"dateId":"February_11","event":"Position","timeMs":1770812681,"worldX":268.56,"worldY":110.42,"worldZ":-47.52,"pixelX":726.54,"pixelY":539.9,"relativeTimeMs":0},{"userId":"86b019b9-dd32-4fe0-baf4-174a1f51fa68","isBot":false,"dateId":"February_11","event":"Position","timeMs":1770812707,"worldX":244.38,"worldY":110.4,"worldZ":-49.37,"pixelX":699.03,"pixelY":542.0,"relativeTimeMs":26},{"userId":"86b019b9-dd32-4fe0-baf4-174a1f51fa68","isBot":false,"dateId":"February_11","event":"Position","timeMs":1770812712,"worldX":218.31,"worldY":110.27,"worldZ":-57.67,"pixelX":669.37,"pixelY":551.45,"relativeTimeMs":31},{"userId":"86b019b9-dd32-4fe0-baf4-174a1f51fa68","isBot":false,"dateId":"February_11","event":"Position","timeMs":1770812717,"worldX":220.98,"worldY":111.7,"worldZ":-79.98,"pixelX":672.41,"pixelY":576.84,"relativeTimeMs":36},{"userId":"86b019b9-dd32-4fe0-baf4-174a1f51fa68","isBot":false,"dateId":"February_11","event":"Position","timeMs":1770812722,"worldX":216.38,"worldY":111.57,"worldZ":-104.44,"pixelX":667.17,"pixelY":604.66,"relativeTimeMs":41},{"userId":"86b019b9-dd32-4fe0-baf4-174a1f51fa68","isBot":false,"dateId":"February_11","event":"Position","timeMs":1770812727,"worldX":214.05,"worldY":111.59,"worldZ":-98.83,"pixelX":664.52,"pixelY":598.28,"relativeTimeMs":46},{"userId":"86b019b9-dd32-4fe0-baf4-174a1f51fa68","isBot":false,"dateId":"February_11","event":"Position","timeMs":1770812732,"worldX":195.76,"worldY":114.47,"worldZ":-83.08,"pixelX":643.71,"pixelY":580.35,"relativeTimeMs":51},{"userId":"86b019b9-dd32-4fe0-baf4-174a1f51fa68","isBot":false,"dateId":"February_11","event":"Position","timeMs":1770812737,"worldX":191.36,"worldY":114.45,"worldZ":-84.25,"pixelX":638.71,"pixelY":581.69,"relativeTimeMs":56},{"userId":"86b019b9-dd32-4fe0-baf4-174a1f51fa68","isBot":false,"dateId":"February_11","event":"Position","timeMs":1770812742,"worldX":170.87,"worldY":106.7,"worldZ":-83.15,"pixelX":615.39,"pixelY":580.44,"relativeTimeMs":61},{"userId":"86b019b9-dd32-4fe0-baf4-174a1f51fa68","isBot":false,"dateId":"February_11","event":"Position","timeMs":1770812747,"worldX":164.69,"worldY":106.82,"worldZ":-63.57,"pixelX":608.36,"pixelY":558.16,"relativeTimeMs":66},{"userId":"86b019b9-dd32-4fe0-baf4-174a1f51fa68","isBot":false,"dateId":"February_11","event":"Loot","timeMs":1770812749,"worldX":160.94,"worldY":106.82,"worldZ":-62.33,"pixelX":604.1,"pixelY":556.75,"relativeTimeMs":68},{"userId":"86b019b9-dd32-4fe0-baf4-174a1f51fa68","isBot":false,"dateId":"February_11","event":"Position","timeMs":1770812752,"worldX":158.76,"worldY":106.82,"worldZ":-66.91,"pixelX":601.61,"pixelY":561.96,"relativeTimeMs":71},{"userId":"86b019b9-dd32-4fe0-baf4-174a1f51fa68","isBot":false,"dateId":"February_11","event":"Position","timeMs":1770812757,"worldX":148.21,"worldY":106.82,"worldZ":-63.3,"pixelX":589.6,"pixelY":557.85,"relativeTimeMs":76},{"userId":"86b019b9-dd32-4fe0-baf4-174a1f51fa68","isBot":false,"dateId":"February_11","event":"Loot","timeMs":1770812761,"worldX":151.43,"worldY":106.82,"worldZ":-69.78,"pixelX":593.27,"pixelY":565.23,"relativeTimeMs":80},{"userId":"86b019b9-dd32-4fe0-baf4-174a1f51fa68","isBot":false,"dateId":"February_11","event":"Position","timeMs":1770812762,"worldX":151.8,"worldY":106.82,"worldZ":-68.36,"pixelX":593.69,"pixelY":563.61,"relativeTimeMs":81},{"userId":"86b019b9-dd32-4fe0-baf4-174a1f51fa68","isBot":false,"dateId":"February_11","event":"Position","timeMs":1770812767,"worldX":148.54,"worldY":106.82,"worldZ":-79.29,"pixelX":589.98,"pixelY":576.05,"relativeTimeMs":86},{"userId":"86b019b9-dd32-4fe0-baf4-174a1f51fa68","isBot":false,"dateId":"February_11","event":"Loot","timeMs":1770812768,"worldX":151.77,"worldY":106.82,"worldZ":-80.16,"pixelX":593.65,"pixelY":577.03,"relativeTimeMs":87},{"userId":"86b019b9-dd32-4fe0-baf4-174a1f51fa68","isBot":false,"dateId":"February_11","event":"Position","timeMs":1770812772,"worldX":156.07,"worldY":106.82,"worldZ":-74.45,"pixelX":598.55,"pixelY":570.54,"relativeTimeMs":91},{"userId":"86b019b9-dd32-4fe0-baf4-174a1f51fa68","isBot":false,"dateId":"February_11","event":"Loot","timeMs":1770812782,"worldX":159.0,"worldY":106.82,"worldZ":-75.27,"pixelX":601.89,"pixelY":571.48,"relativeTimeMs":101},{"userId":"86b019b9-dd32-4fe0-baf4-174a1f51fa68","isBot":false,"dateId":"February_11","event":"Position","timeMs":1770812782,"worldX":158.98,"worldY":106.82,"worldZ":-75.46,"pixelX":601.86,"pixelY":571.69,"relativeTimeMs":101},{"userId":"86b019b9-dd32-4fe0-baf4-174a1f51fa68","isBot":false,"dateId":"February_11","event":"Position","timeMs":1770812787,"worldX":168.82,"worldY":106.7,"worldZ":-69.05,"pixelX":613.06,"pixelY":564.4,"relativeTimeMs":106},{"userId":"86b019b9-dd32-4fe0-baf4-174a1f51fa68","isBot":false,"dateId":"February_11","event":"Position","timeMs":1770812792,"worldX":152.41,"worldY":106.71,"worldZ":-46.15,"pixelX":594.38,"pixelY":538.33,"relativeTimeMs":111},{"userId":"86b019b9-dd32-4fe0-baf4-174a1f51fa68","isBot":false,"dateId":"February_11","event":"Position","timeMs":1770812797,"worldX":132.21,"worldY":106.7,"worldZ":-68.25,"pixelX":571.41,"pixelY":563.49,"relativeTimeMs":116},{"userId":"86b019b9-dd32-4fe0-baf4-174a1f51fa68","isBot":false,"dateId":"February_11","event":"Position","timeMs":1770812802,"worldX":119.17,"worldY":106.69,"worldZ":-76.91,"pixelX":556.57,"pixelY":573.34,"relativeTimeMs":121},{"userId":"86b019b9-dd32-4fe0-baf4-174a1f51fa68","isBot":false,"dateId":"February_11","event":"BotKill","timeMs":1770812807,"worldX":120.85,"worldY":106.83,"worldZ":-83.58,"pixelX":558.48,"pixelY":580.92,"relativeTimeMs":126},{"userId":"86b019b9-dd32-4fe0-baf4-174a1f51fa68","isBot":false,"dateId":"February_11","event":"Position","timeMs":1770812807,"worldX":120.68,"worldY":106.82,"worldZ":-84.74,"pixelX":558.29,"pixelY":582.24,"relativeTimeMs":126},{"userId":"86b019b9-dd32-4fe0-baf4-174a1f51fa68","isBot":false,"dateId":"February_11","event":"Position","timeMs":1770812812,"worldX":124.05,"worldY":106.81,"worldZ":-93.92,"pixelX":562.12,"pixelY":592.7,"relativeTimeMs":131},{"userId":"86b019b9-dd32-4fe0-baf4-174a1f51fa68","isBot":false,"dateId":"February_11","event":"BotKilled","timeMs":1770812821,"worldX":121.12,"worldY":106.81,"worldZ":-94.38,"pixelX":558.79,"pixelY":593.22,"relativeTimeMs":140}],"eventPoints":[{"id":"018ce847-fe23-405e-a6c0-48ba53766681.nakama-0:0","userId":"86b019b9-dd32-4fe0-baf4-174a1f51fa68","isBot":false,"dateId":"February_11","event":"Loot","timeMs":1770812749,"worldX":160.94,"worldY":106.82,"worldZ":-62.33,"pixelX":604.1,"pixelY":556.75,"relativeTimeMs":68},{"id":"018ce847-fe23-405e-a6c0-48ba53766681.nakama-0:1","userId":"86b019b9-dd32-4fe0-baf4-174a1f51fa68","isBot":false,"dateId":"February_11","event":"Loot","timeMs":1770812761,"worldX":151.43,"worldY":106.82,"worldZ":-69.78,"pixelX":593.27,"pixelY":565.23,"relativeTimeMs":80},{"id":"018ce847-fe23-405e-a6c0-48ba53766681.nakama-0:2","userId":"86b019b9-dd32-4fe0-baf4-174a1f51fa68","isBot":false,"dateId":"February_11","event":"Loot","timeMs":1770812768,"worldX":151.77,"worldY":106.82,"worldZ":-80.16,"pixelX":593.65,"pixelY":577.03,"relativeTimeMs":87},{"id":"018ce847-fe23-405e-a6c0-48ba53766681.nakama-0:3","userId":"86b019b9-dd32-4fe0-baf4-174a1f51fa68","isBot":false,"dateId":"February_11","event":"Loot","timeMs":1770812782,"worldX":159.0,"worldY":106.82,"worldZ":-75.27,"pixelX":601.89,"pixelY":571.48,"relativeTimeMs":101},{"id":"018ce847-fe23-405e-a6c0-48ba53766681.nakama-0:4","userId":"86b019b9-dd32-4fe0-baf4-174a1f51fa68","isBot":false,"dateId":"February_11","event":"BotKill","timeMs":1770812807,"worldX":120.85,"worldY":106.83,"worldZ":-83.58,"pixelX":558.48,"pixelY":580.92,"relativeTimeMs":126},{"id":"018ce847-fe23-405e-a6c0-48ba53766681.nakama-0:5","userId":"86b019b9-dd32-4fe0-baf4-174a1f51fa68","isBot":false,"dateId":"February_11","event":"BotKilled","timeMs":1770812821,"worldX":121.12,"worldY":106.81,"worldZ":-94.38,"pixelX":558.79,"pixelY":593.22,"relativeTimeMs":140}]}